quspin_extensions/__init__.py
quspin_extensions/basis/__init__.py
quspin_extensions/basis/_basis_utils.cpython-311-darwin.so
quspin_extensions/basis/_basis_utils.cpp
quspin_extensions/basis/basis_general/__init__.py
quspin_extensions/basis/basis_general/_basis_general_core/spinful_fermion_core.cpp
quspin_extensions/basis/basis_general/_basis_general_core/user_core.cpython-311-darwin.so
quspin_extensions/basis/basis_general/_basis_general_core/general_basis_utils.cpp
quspin_extensions/basis/basis_general/_basis_general_core/__init__.py
quspin_extensions/basis/basis_general/_basis_general_core/spinless_fermion_core.cpython-311-darwin.so
quspin_extensions/basis/basis_general/_basis_general_core/general_basis_utils.cpython-311-darwin.so
quspin_extensions/basis/basis_general/_basis_general_core/boson_core.cpp
quspin_extensions/basis/basis_general/_basis_general_core/hcb_core.cpython-311-darwin.so
quspin_extensions/basis/basis_general/_basis_general_core/user_core.cpp
quspin_extensions/basis/basis_general/_basis_general_core/higher_spin_core.cpp
quspin_extensions/basis/basis_general/_basis_general_core/boson_core.cpython-311-darwin.so
quspin_extensions/basis/basis_general/_basis_general_core/spinless_fermion_core.cpp
quspin_extensions/basis/basis_general/_basis_general_core/higher_spin_core.cpython-311-darwin.so
quspin_extensions/basis/basis_general/_basis_general_core/hcb_core.cpp
quspin_extensions/basis/basis_general/_basis_general_core/spinful_fermion_core.cpython-311-darwin.so
quspin_extensions/basis/basis_general/_basis_general_core/source/spinful_fermion_basis_core.h
quspin_extensions/basis/basis_general/_basis_general_core/source/general_basis_bitops.h
quspin_extensions/basis/basis_general/_basis_general_core/source/misc.h
quspin_extensions/basis/basis_general/_basis_general_core/source/general_basis_rep.h
quspin_extensions/basis/basis_general/_basis_general_core/source/spinless_fermion_basis_core.h
quspin_extensions-0.1.6.dist-info/RECORD
quspin_extensions-0.1.6.dist-info/LICENSE
quspin_extensions-0.1.6.dist-info/WHEEL
quspin_extensions-0.1.6.dist-info/top_level.txt
quspin_extensions-0.1.6.dist-info/METADATA
