Metadata-Version: 2.1
Name: quspin-extensions
Version: 0.1.6
Summary: C++ extensions for QuSpin
Author-email: Phillip Weinberg <weinbe58@gmail.com>, Marin Bukov <mbukov@gmail.com>
License: BSD-3-Clause
Classifier: Development Status :: 3 - Alpha
Classifier: Operating System :: Microsoft :: Windows
Classifier: Operating System :: MacOS
Classifier: Operating System :: POSIX :: Linux
Classifier: Programming Language :: Python :: 3.9
Classifier: Programming Language :: Python :: 3.10
Classifier: Programming Language :: Python :: 3.11
Classifier: Programming Language :: Python :: 3.12
Requires-Python: <3.13,>=3.9
License-File: LICENSE
Requires-Dist: numpy
Requires-Dist: scipy
Requires-Dist: gmpy2>=2.2.0
